mohe_mcp_server/__init__.py
mohe_mcp_server/__main__.py
mohe_mcp_server/ant.jpg
mohe_mcp_server/ant.py
mohe_mcp_server/server.py
mohe_mcp_server-0.1.4.dist-info/METADATA
mohe_mcp_server-0.1.4.dist-info/WHEEL
mohe_mcp_server-0.1.4.dist-info/entry_points.txt
mohe_mcp_server-0.1.4.dist-info/RECORD
